prometheus_edqt/__init__.py
prometheus_edqt/guardian.py
prometheus_edqt/optimizer.py
prometheus_edqt-1.0.0.dist-info/licenses/LICENSE
prometheus_edqt-1.0.0.dist-info/METADATA
prometheus_edqt-1.0.0.dist-info/WHEEL
prometheus_edqt-1.0.0.dist-info/top_level.txt
prometheus_edqt-1.0.0.dist-info/RECORD
