Metadata-Version: 2.4
Name: prometheus-edqt
Version: 1.0.0
Summary: Riemannian Manifold Optimization & Telemetric Integrity for AI Tensors
Home-page: https://github.com/Prometheus-Lab-Core/prometheus-edqt
Author: Prometheus Open Science Foundation
Author-email: contact@prometheus-science.org
Keywords: ai machine-learning manifold-optimization information-geometry edqt-standard
Classifier: Development Status :: 5 - Production/Stable
Classifier: Intended Audience :: Science/Research
Classifier: Topic :: Scientific/Engineering :: Artificial Intelligence
Classifier: Topic :: Scientific/Engineering :: Mathematics
Classifier: License :: OSI Approved :: Apache Software License
Classifier: Programming Language :: Python :: 3.9
Classifier: Programming Language :: Python :: 3.10
Requires-Python: >=3.9
License-File: LICENSE
Requires-Dist: numpy>=1.21.0
Requires-Dist: scipy>=1.7.0
Requires-Dist: requests>=2.26.0
Requires-Dist: cryptography>=3.4.0
Dynamic: author
Dynamic: author-email
Dynamic: classifier
Dynamic: description
Dynamic: description-content-type
Dynamic: home-page
Dynamic: keywords
Dynamic: license-file
Dynamic: requires-dist
Dynamic: requires-python
Dynamic: summary
